iotmeter_api.py
iotmeter_api-1.0.2.dist-info/METADATA
iotmeter_api-1.0.2.dist-info/WHEEL
iotmeter_api-1.0.2.dist-info/top_level.txt
iotmeter_api-1.0.2.dist-info/RECORD
