Metadata-Version: 2.1
Name: iotmeter-api
Version: 1.0.2
Summary: A Python library to interact with IoT Meter devices
Home-page: https://github.com/lipic/iotmeter_api
Author: lipic
Author-email: info@vilmio.com
Classifier: Programming Language :: Python :: 3
Classifier: License :: OSI Approved :: MIT License
Classifier: Operating System :: OS Independent
Requires-Python: >=3.6
Requires-Dist: aiohttp>=3.8.1
